manver/__init__.py
manver/__main__.py
manver/cli.py
manver/lib.py
manver-1.0.0.dist-info/entry_points.txt
manver-1.0.0.dist-info/WHEEL
manver-1.0.0.dist-info/METADATA
manver-1.0.0.dist-info/RECORD
